parse_me/__init__.py
parse_me/name_parsing_agent.py
parse_me/name_parsing_prompts.py
parse_me/parse.py
parse_me/test_package.py
test/convert_tsv.py
test/test_parser.py
parse_me-0.2.0.dist-info/METADATA
parse_me-0.2.0.dist-info/WHEEL
parse_me-0.2.0.dist-info/top_level.txt
parse_me-0.2.0.dist-info/RECORD
