Metadata-Version: 2.1
Name: parse_me
Version: 0.2.0
Summary: An AI-backed name parsing package for Middle-Eastern and Other languages. 
Author-email: Tomer Sagi <tsagi@cs.aau.dk>, Sinai Rusinek <sinai.rusinek@gmail.com>, Moran Zaga <mzaga@Staff.haifa.ac.il>
Project-URL: Homepage, https://mehdie.org/
Project-URL: Bug Tracker, https://gitlab.com/m8417/mehdie-arabic-name-parser/-/issues
Classifier: Programming Language :: Python :: 3
Classifier: License :: OSI Approved :: Apache Software License
Classifier: Operating System :: OS Independent
Requires-Python: >=3.9
